Metadata-Version: 2.1
Name: sysconx4
Version: 0.1.1
Summary: package for pentesting
Author: superuser
